{
  "numID": 5,
  "_id": "lesson_5_en-US",
  "ShortTitle": "ILikeThat",
  "PublicationStatus": "Live",
  "Language": "English",
  "Country": "United States",
  "DefaultLanguage": "English",
  "DefaultCountry": "United States",
  "LastUpdated": "2023-12-15 17:49:33.234319",
  "ReleaseDate": "2022-10-31",
  "isTestRepo": false,
  "FirstPublicationDate": "2022-07-11 21:10:05",
  "LsnStatuses": [
    {
      "lsn": 1,
      "status": "Live",
      "updated_date": null,
      "new_date": "2022-10-31",
      "sort_by_date": "2022-10-31"
    },
    {
      "lsn": 2,
      "status": "Live",
      "updated_date": null,
      "new_date": "2022-10-31",
      "sort_by_date": "2022-10-31"
    },
    {
      "lsn": 3,
      "status": "Live",
      "updated_date": null,
      "new_date": "2022-10-31",
      "sort_by_date": "2022-10-31"
    }
  ],
  "MediumTitle": "'I Like That!' |Science| G5-9 (en-US)",
  "lang": "en",
  "lng": "eng",
  "locale": "en-US",
  "DefaultLocale": "en-US",
  "TemplateVer": "0.6.2",
  "galacticPubsVer": "0.9.8",
  "URL": "https://www.galacticpolymath.com/lessons/en-US/5",
  "GdriveHome": "GP-LIVE",
  "GdriveDirName": "ILikeThat_en-US",
  "GdriveTeachMatPath": "GalacticPolymath/'I Like That!' |Science| G5-9 (en-US)",
  "GdriveTeachMatID": null,
  "GdrivePublicID": "1UXpy8XV17eKX5qZ4ALEeGc9IEt1IEuIf",
  "GdriveDirID": "1Nxy1V4pf21NhElAUdqVZpdinqCPi1oh3",
  "GdriveMetaID": "1eC6wRn9rqFLLmsV_SKf3TSxSRnKDJf17",
  "GdriveTeachItID": "173XD1xQd6dQt45m1NGhmM3lP9LRd5FWo-gn5mmmaSuM",
  "GdriveStandardsID": "1dSjqy3VjBn_qKEFWjp5ElJFQ98b7Mm4YnSApAZUKf9A",
  "GdrivePublishedID": "1qORPugrPSBLwCew3wSEwzmmbVjTnkKOJ",
  "GdriveDirURL": "https://drive.google.com/drive/folders/1Nxy1V4pf21NhElAUdqVZpdinqCPi1oh3",
  "RebuildAllMaterials": false,
  "Title": "I Like That!",
  "Subtitle": "How perception, emotion, and cognition shape our preferences",
  "SponsorName": ["NSF", "Tamra Mendelson Lab", "University of Maryland–Baltimore County"],
  "SponsoredBy": "- The National Science Foundation\n- [Dr. Tamra Mendelson's Lab](https://www.mendelsonlab.net/) in the Department of Biological Sciences at the University of Maryland, Baltimore County",
  "SponsorLogo": ["https://storage.googleapis.com/gp-cloud/lessons/ILikeThat_en-US/NSF_4-Color_bitmap_Logo@0.25x.png", "https://storage.googleapis.com/gp-cloud/lessons/ILikeThat_en-US/UMBC-vertical-logo-RGB-195x300.png"],
  "LessonBanner": "https://storage.googleapis.com/gp-cloud/lessons/ILikeThat_en-US/banner-100.jpg",
  "LessonCard": "https://storage.googleapis.com/gp-cloud/lessons/ILikeThat_en-US/title_card-100.jpg",
  "TargetSubject": "Science",
  "LessonEnvir": "Classroom",
  "ForGrades": "5-9",
  "GradesOrYears": "Grades"
}
